{
  "document_type": "administratif",
  "content": "P a g e 1 | 1 Vandœuvre les Nancy, le 10 octobre 2022 Communiqué de presse Une 35e école rejoint le concours Geipi Polytech Le concours Geipi Polytech, concours d’entrée post bac en écoles d’ingénieurs publiques, intègre une nouvelle école dans son groupement à partir de l’édition 2023 : l’ESIR, Ecole Supérieure d’Ingénieurs de Rennes, composante de l’université de Rennes 1. Les directeurs des écoles d’ingénieurs du groupement Geipi Polytech se sont réunis en assemblée générale, les 29 et 30 septembre, à Valence. L’assemblée a voté l’entrée de l’ESIR, Ecole Supérieure d’Ingénieurs de Rennes, dans le concours Geipi Polytech à partir de l’édition 2023. Cela porte ainsi le nombre d’écoles partenaires à 35 : L’Institut Agro et ESIREM à Dijon, EEIGM et ENSGSI à Nancy, ENIB Brest, ENIM Metz, ENISE Saint- Etienne, INP-ENIT Tarbes, ENSIM et ESGT au Mans, ENSIBS Lorient-Vannes, ESIR Rennes, ESIROI La Réunion, Grenoble-INP Esisar Valence, IMT Nord Europe, ISAT Nevers, ISEL Le Havre, ISTY Mantes-Vélizy, SupGalilée Paris, Télécom Saint-Etienne et les 15 écoles du Réseau Polytech (Angers, Annecy-Chambéry, Clermont, Marseille, Grenoble, Lille, Lyon, Montpellier, Nancy, Nantes, Nice Sophia, Orléans, Paris-Saclay, Sorbonne, Tours). L’ESIR Rennes proposera 65 places en 2023 aux élèves de Terminale générale, qui pourront ensuite s’orienter vers l’une des spécialités offertes par l’école :  Informatique  Matériaux  Systèmes Numériques et Réseaux  Technologies de l’Information pour la Santé Les inscriptions au concours Geipi Polytech se dérouleront du 18 janvier au 8 mars 2023 sur la plateforme Parcoursup : www.parcoursup.fr Contacts presse : Caroline SCHWARTZ, Chargée de communication - Tél. : 03.72.74.68.39 - communication@geipi-polytech.org Agnès MANGEL, Responsable administrative - Tél. 03.72.74.68.38 – agnes.mangel@geipi-polytech.org",
  "metadata": {
    "title": "Cp geipi polytech une nouvelle ecole octobre 2022",
    "secteur": "",
    "date": "2022-10-07T13:39:44",
    "auteurs": [
      "l’ESIR",
      "Ecole Supérieure"
    ]
  },
  "source": {
    "chemin_local": "/home/adrien/Documents/poly4emeAnee/Projet-Stage/Projet-Chatbot/Document_handler/scraping/data_sites/geipi_polytech/pdf_scrapes/cp_geipi_polytech_une_nouvelle_ecole_octobre_2022.pdf",
    "site": "scraped_geipi",
    "url": "https://www.geipi-polytech.org/presse/"
  },
  "tags": [
    "Geipi Polytech",
    "ESIR",
    "école d'ingénieurs",
    "concours d'entrée",
    "Rennes",
    "Terminale générale",
    "spécialités",
    "Informatique",
    "Matériaux",
    "Systèmes Numériques",
    "Technologies de l'Information",
    "Parcoursup",
    "écoles partenaires",
    "communication",
    "assemblée générale"
  ],
  "type_specific": {
    "administratif": {
      "service": "Geipi Polytech",
      "contact": {
        "email": "communication@geipi-polytech.org",
        "telephone": "03.72.74.68.39"
      }
    }
  }
}